{
  "$schema": "https://turbo.build/schema.json",
  "globalEnv": [
    "NODE_ENV",
    "SUPABASE_URL",
    "SUPABASE_ANON_KEY",
    "SUPABASE_SERVICE_ROLE_KEY",
    "STRIPE_SECRET_KEY",
    "STRIPE_WEBHOOK_SECRET",
    "DATABASE_URL"
  ],
  "tasks": {
    "build": {
      "dependsOn": ["^build"],
      "outputs": ["dist/**", ".next/**", "!.next/cache/**"]
    },
    "dev": {
      "cache": false,
      "persistent": true
    },
    "test": {
      "dependsOn": ["^build"],
      "outputs": ["coverage/**"]
    },
    "lint": {
      "outputs": []
    },
    "clean": {
      "cache": false
    }
  }
}
